LAGEF_UFF/LAGEF_UFF_linha_de_costa.py
LAGEF_UFF/__init__.py
LAGEF_UFF_Linha_de_costa-0.0.4.dist-info/LICENCE
LAGEF_UFF_Linha_de_costa-0.0.4.dist-info/METADATA
LAGEF_UFF_Linha_de_costa-0.0.4.dist-info/WHEEL
LAGEF_UFF_Linha_de_costa-0.0.4.dist-info/top_level.txt
LAGEF_UFF_Linha_de_costa-0.0.4.dist-info/RECORD
