Metadata-Version: 2.2
Name: LAGEF-UFF-Linha_de_costa
Version: 0.0.4
Summary: Scripts para análise de linha de costa
Author: Pablo Simoes
Author-email: pablosergio.simoes@gmail.com
License: MIT License
Keywords: lagef uff,linha de costa,google earth engine
License-File: LICENCE
Requires-Dist: pandas
Requires-Dist: geemap
Requires-Dist: numpy
Requires-Dist: earthengine-api
Requires-Dist: scikit-image
Requires-Dist: matplotlib
Dynamic: author
Dynamic: author-email
Dynamic: description
Dynamic: description-content-type
Dynamic: keywords
Dynamic: license
Dynamic: requires-dist
Dynamic: summary
